fast2sms/__init__.py
fast2sms/client.py
fast2sms-1.0.0.dist-info/LICENSE
fast2sms-1.0.0.dist-info/METADATA
fast2sms-1.0.0.dist-info/WHEEL
fast2sms-1.0.0.dist-info/top_level.txt
fast2sms-1.0.0.dist-info/RECORD
