Metadata-Version: 2.1
Name: fast2sms
Version: 1.0.0
Summary: Python package for Fast2 Sms API Client
Home-page: https://github.com/MrMKN/fast2sms
Author: MrMKN
License: GNU General Public License v3.0
Classifier: Programming Language :: Python :: 3
Classifier: License :: OSI Approved :: GNU Lesser General Public License v3 or later (LGPLv3+)
Classifier: Operating System :: OS Independent
Requires-Python: >=3.6
License-File: LICENSE
